{
  "shift_tasks": [
    {
      "id": "ST001",
      "managerId": "E005",
      "taskType": "shift_approval",
      "title": "Approve Team Schedule for Next Week",
      "description": "Review and approve requested schedules for the engineering team for next week",
      "status": "pending",
      "dueDate": "2024-03-08",
      "priority": "high",
      "departmentId": "D001",
      "relatedItems": ["schedule-requests", "coverage-requirements", "approval-form"],
      "notes": "Pay special attention to coverage for the production deployment on Wednesday"
    },
    {
      "id": "ST002",
      "managerId": "E007",
      "taskType": "shift_planning",
      "title": "Create Q2 Schedule Plan",
      "description": "Develop the marketing team schedule plan for Q2, considering campaign deadlines",
      "status": "in_progress",
      "dueDate": "2024-03-20",
      "priority": "medium",
      "departmentId": "D002",
      "relatedItems": ["campaign-calendar", "team-availability", "scheduling-template"],
      "notes": "Ensure adequate coverage for the product launch events in April"
    },
    {
      "id": "ST003",
      "managerId": "E008",
      "taskType": "time_off_approval",
      "title": "Process Time Off Requests",
      "description": "Review and respond to pending time off requests for the sales team",
      "status": "in_progress",
      "dueDate": "2024-03-09",
      "priority": "high",
      "departmentId": "D003",
      "relatedItems": ["time-off-requests", "coverage-calendar", "approval-form"],
      "notes": "Several requests for the spring break period need coordination"
    },
    {
      "id": "ST004",
      "managerId": "E009",
      "taskType": "shift_coverage",
      "title": "Address HR Department Coverage Gap",
      "description": "Find coverage for HR support during team training session next week",
      "status": "pending",
      "dueDate": "2024-03-12",
      "priority": "high",
      "departmentId": "D004",
      "relatedItems": ["team-schedule", "training-agenda", "coverage-options"],
      "notes": "Need at least one HR representative available during business hours"
    },
    {
      "id": "ST005",
      "managerId": "E005",
      "taskType": "schedule_change",
      "title": "Process Schedule Change Request",
      "description": "Review and process schedule change request from John Smith",
      "status": "completed",
      "dueDate": "2024-03-05",
      "completedDate": "2024-03-04",
      "priority": "medium",
      "departmentId": "D001",
      "employeeId": "E001",
      "relatedItems": ["change-request-form", "current-schedule", "approval-form"],
      "notes": "Employee needs to adjust hours for medical appointment"
    },
    {
      "id": "ST006",
      "managerId": "E011",
      "taskType": "shift_assignment",
      "title": "Assign Coverage for Evening Support",
      "description": "Schedule team members for extended evening support hours next week",
      "status": "pending",
      "dueDate": "2024-03-10",
      "priority": "medium",
      "departmentId": "D005",
      "relatedItems": ["team-availability", "support-requirements", "schedule-template"],
      "notes": "Need coverage until 8 PM for the product release support"
    },
    {
      "id": "ST007",
      "managerId": "E010",
      "taskType": "overtime_approval",
      "title": "Review Overtime Requests",
      "description": "Review and approve overtime requests for the month-end processing",
      "status": "in_progress",
      "dueDate": "2024-03-15",
      "priority": "medium",
      "relatedItems": ["overtime-requests", "budget-impact", "approval-workflow"],
      "notes": "Consider budget implications for each department"
    },
    {
      "id": "ST008",
      "managerId": "E005",
      "taskType": "rotation_planning",
      "title": "Set Up On-Call Rotation for April",
      "description": "Organize and communicate the on-call rotation schedule for April",
      "status": "not_started",
      "dueDate": "2024-03-25",
      "priority": "medium",
      "departmentId": "D001",
      "relatedItems": ["team-availability", "on-call-requirements", "rotation-template"],
      "notes": "Ensure fair distribution of weekend and holiday coverage"
    },
    {
      "id": "ST009",
      "managerId": "E008",
      "taskType": "schedule_review",
      "title": "Review Q1 Time and Attendance",
      "description": "Review time and attendance records for Q1 for the sales team",
      "status": "not_started",
      "dueDate": "2024-04-05",
      "priority": "low",
      "departmentId": "D003",
      "relatedItems": ["attendance-records", "time-reports", "policy-guidelines"],
      "notes": "Identify any patterns that need addressing in one-on-one meetings"
    },
    {
      "id": "ST010",
      "managerId": "E009",
      "taskType": "holiday_planning",
      "title": "Finalize Summer Holiday Coverage",
      "description": "Finalize the coverage plan for the summer holiday period",
      "status": "in_progress",
      "dueDate": "2024-03-31",
      "priority": "medium",
      "relatedItems": ["holiday-calendar", "time-off-requests", "coverage-requirements"],
      "notes": "Ensure critical functions are covered during peak vacation season"
    }
  ]
}